exercises/CSARCH1/HDL/sample_2/simple_circuit.v
`timescale 1ns/1ps

// User-defined Primitives Modelling (truth table)

module simple_circuit(D, E, A, B, C);
	input A, B, C;
	output D, E;
	
    UDP_D(D, A, B, C);
    UDP_E(E, A, B, C);
	
endmodule

primitive UDP_D(D, A, B, C);
    output D;
    input A, B, C;

    table 
    // A B C : D
        0 0 0 : 1;
        0 0 1 : 0;
        0 1 0 : 1;
        0 1 1 : 0;
        1 0 0 : 1;
        1 0 1 : 0;
        1 1 0 : 1;
        1 1 1 : 1;
    endtable
endprimitive


primitive UDP_E(E, A, B, C);
    output E;
    input A, B, C;

    table 
    // A B C : E
        0 0 0 : 1;
        0 0 1 : 0;
        0 1 0 : 1;
        0 1 1 : 0;
        1 0 0 : 1;
        1 0 1 : 0;
        1 1 0 : 1;
        1 1 1 : 0;
    endtable
endprimitive

exercises/CSARCH1/HDL/sample_2/simple_circuit_tb.v
`timescale 1ns/1ps

module simple_circuit_tb ();
    reg t_A, t_B, t_C;
    wire t_D, t_E;

    simple_circuit dut(t_D, t_E, t_A, t_B, t_C);
    
    initial begin
        t_A = 0; t_B = 0; t_C = 0;
        #10 t_A = 0; t_B = 0; t_C = 1;
        #10 t_A = 0; t_B = 1; t_C = 0;
        #10 t_A = 0; t_B = 1; t_C = 1;
        #10 t_A = 1; t_B = 0; t_C = 0;
        #10 t_A = 1; t_B = 0; t_C = 1;
        #10 t_A = 1; t_B = 1; t_C = 0;
        #10 t_A = 1; t_B = 1; t_C = 1;
        #10 $finish;
    end

    initial begin
        $monitor("time = %d: A = %b B = %b C = %b | D = %b E = %b",
        $time, t_A, t_B, t_C, t_D, t_E);
        $dumpfile("simple_circuit.vcd");
        $dumpvars(0, simple_circuit_tb);
    end

endmodule

lab/CSARCH1/HDL/sample_2/simple_circuit.vcd
$date
	Mon Feb 16 14:16:28 2026
$end
$version
	Icarus Verilog
$end
$timescale
	1ps
$end
$scope module simple_circuit_tb $end
$var wire 1 ! t_E $end
$var wire 1 " t_D $end
$var reg 1 # t_A $end
$var reg 1 $ t_B $end
$var reg 1 % t_C $end
$scope module dut $end
$var wire 1 # A $end
$var wire 1 $ B $end
$var wire 1 % C $end
$var wire 1 " D $end
$var wire 1 ! E $end
$upscope $end
$upscope $end
$enddefinitions $end
$comment Show the parameter values. $end
$dumpall
$end
#0
$dumpvars
0%
0$
0#
1"
1!
$end
#10000
0"
0!
1%
#20000
1"
1!
0%
1$
#30000
0"
0!
1%
#40000
1!
1"
0%
0$
1#
#50000
0"
0!
1%
#60000
1!
1"
0%
1$
#70000
0!
1%
