exercises/CSARCH1/HDL/sample_1/simple_circuit.v
`timescale 1ns/1ps

// Gate-level Modelling (circuit diagram)

module simple_circuit(D, E, A, B, C);
	input A, B, C;
	output D, E;
	wire w1;
	
	and G1(w1, A, B);
	not G2(E, C);
	or G3(D, w1, E);
endmodule

exercises/CSARCH1/HDL/sample_2/simple_circuit_tb.v
`timescale 1ns/1ps

module simple_circuit_tb ();
    reg t_A, t_B, t_C;
    wire t_D, t_E;

    simple_circuit dut(t_D, t_E, t_A, t_B, t_C);
    
    initial begin
        t_A = 0; t_B = 0; t_C = 0;
        #10 t_A = 0; t_B = 0; t_C = 1;
        #10 t_A = 0; t_B = 1; t_C = 0;
        #10 t_A = 0; t_B = 1; t_C = 1;
        #10 t_A = 1; t_B = 0; t_C = 0;
        #10 t_A = 1; t_B = 0; t_C = 1;
        #10 t_A = 1; t_B = 1; t_C = 0;
        #10 t_A = 1; t_B = 1; t_C = 1;
        #10 $finish;
    end

    initial begin
        $monitor("time = %d: A = %b B = %b C = %b | D = %b E = %b",
        $time, t_A, t_B, t_C, t_D, t_E);
        $dumpfile("simple_circuit.vcd");
        $dumpvars(0, simple_circuit_tb);
    end

endmodule

lab/CSARCH1/HDL/sample_1/simple_circuit.vcd
$date
	Mon Feb 16 13:49:16 2026
$end
$version
	Icarus Verilog
$end
$timescale
	1ps
$end
$scope module simple_circuit_tb $end
$var wire 1 ! t_E $end
$var wire 1 " t_D $end
$var reg 1 # t_A $end
$var reg 1 $ t_B $end
$var reg 1 % t_C $end
$scope module dut $end
$var wire 1 # A $end
$var wire 1 $ B $end
$var wire 1 % C $end
$var wire 1 " D $end
$var wire 1 ! E $end
$var wire 1 & w1 $end
$upscope $end
$upscope $end
$enddefinitions $end
$comment Show the parameter values. $end
$dumpall
$end
#0
$dumpvars
0&
0%
0$
0#
1"
1!
$end
#10000
0"
0!
1%
#20000
1"
1!
0%
1$
#30000
0"
0!
1%
#40000
1"
1!
0%
0$
1#
#50000
0"
0!
1%
#60000
1"
1!
1&
0%
1$
#70000
0!
1%
